dtool_lookup_gui/.gitignore
dtool_lookup_gui/__init__.py
dtool_lookup_gui/__main__.py
dtool_lookup_gui/de.uni-freiburg.dtool-lookup-gui.gresource.xml
dtool_lookup_gui/de.uni-freiburg.dtool-lookup-gui.gschema.xml
dtool_lookup_gui/gschemas.compiled
dtool_lookup_gui/launcher.py
dtool_lookup_gui/main.py
dtool_lookup_gui/version.py
dtool_lookup_gui/models/__init__.py
dtool_lookup_gui/models/base_uris.py
dtool_lookup_gui/models/datasets.py
dtool_lookup_gui/models/search_state.py
dtool_lookup_gui/models/settings.py
dtool_lookup_gui/models/simple_graph.py
dtool_lookup_gui/utils/__init__.py
dtool_lookup_gui/utils/about.py
dtool_lookup_gui/utils/copy_manager.py
dtool_lookup_gui/utils/date.py
dtool_lookup_gui/utils/dependency_graph.py
dtool_lookup_gui/utils/environ.py
dtool_lookup_gui/utils/logging.py
dtool_lookup_gui/utils/multiprocessing.py
dtool_lookup_gui/utils/progressbar.py
dtool_lookup_gui/utils/query.py
dtool_lookup_gui/utils/subprocess.py
dtool_lookup_gui/views/__init__.py
dtool_lookup_gui/views/about_dialog.py
dtool_lookup_gui/views/about_dialog.ui
dtool_lookup_gui/views/authentication_dialog.py
dtool_lookup_gui/views/authentication_dialog.ui
dtool_lookup_gui/views/config_details.py
dtool_lookup_gui/views/config_details.ui
dtool_lookup_gui/views/dataset_name_dialog.py
dtool_lookup_gui/views/dataset_name_dialog.ui
dtool_lookup_gui/views/error_linting_dialog.py
dtool_lookup_gui/views/error_linting_dialog.ui
dtool_lookup_gui/views/log_window.py
dtool_lookup_gui/views/log_window.ui
dtool_lookup_gui/views/login_window.py
dtool_lookup_gui/views/login_window.ui
dtool_lookup_gui/views/main_window.py
dtool_lookup_gui/views/main_window.ui
dtool_lookup_gui/views/s3_configuration_dialog.py
dtool_lookup_gui/views/s3_configuration_dialog.ui
dtool_lookup_gui/views/server_versions_dialog.py
dtool_lookup_gui/views/server_versions_dialog.ui
dtool_lookup_gui/views/settings_dialog.py
dtool_lookup_gui/views/settings_dialog.ui
dtool_lookup_gui/views/smb_configuration_dialog.py
dtool_lookup_gui-0.7.2.dist-info/licenses/LICENSE-MIT.md
dtool_lookup_gui-0.7.2.dist-info/licenses/LICENSE.md
dtool_lookup_gui-0.7.2.dist-info/licenses/LICENSE.txt
dtool_lookup_gui-0.7.2.dist-info/METADATA
dtool_lookup_gui-0.7.2.dist-info/WHEEL
dtool_lookup_gui-0.7.2.dist-info/entry_points.txt
dtool_lookup_gui-0.7.2.dist-info/top_level.txt
dtool_lookup_gui-0.7.2.dist-info/RECORD
