Metadata-Version: 2.4
Name: dtool-lookup-gui
Version: 0.7.2
Summary: Graphical user interface for dtool
Author-email: "Johannes L. Hoermann" <johannes.hoermann@imtek.uni-freiburg.de>, Lars Pastewka <lars.pastewka@imtek.uni-freiburg.de>
License: # LICENSE
Project-URL: documentation, https://dtool-lookup-gui.readthedocs.io
Project-URL: repository, https://github.com/livMatS/dtool-lookup-gui
Project-URL: changelog, https://dtool-lookup-gui.readthedocs.io/en/latest/changelog.html
Keywords: research data management,dtool
Classifier: Programming Language :: Python :: 3
Classifier: License :: OSI Approved :: MIT License
Classifier: Operating System :: OS Independent
Requires-Python: >=3.9
License-File: LICENSE-MIT.md
License-File: LICENSE.md
License-File: LICENSE.txt
Requires-Dist: dtoolcore>=3.19.0
Requires-Dist: dtool-create>=0.23.4
Requires-Dist: dtool-info>=0.16.2
Requires-Dist: dtool-lookup-api>=0.10.3
Requires-Dist: aiohttp>=3.6
Requires-Dist: pyyaml>=5.3
Requires-Dist: ruamel.yaml
Requires-Dist: PyGObject>=3.50
Requires-Dist: scipy>=1.5
Requires-Dist: numpy
Requires-Dist: jwt
Requires-Dist: yamllint
Provides-Extra: test
Requires-Dist: dtool-s3; extra == "test"
Requires-Dist: dtool-smb; extra == "test"
Requires-Dist: pytest; extra == "test"
Requires-Dist: pytest-cov; extra == "test"
Requires-Dist: pytest-asyncio; extra == "test"
Requires-Dist: pytest-flake8; extra == "test"
Requires-Dist: pytest-xdist; extra == "test"
Dynamic: license-file
